glean/__init__.py
glean/config.py
glean/glean.py
glean/api/__init__.py
glean/api/base.py
glean/api/client.py
glean/api/index.py
glean/api/utils.py
glean/models/__init__.py
glean/models/base.py
glean/models/helper.py
glean/models/people.py
glean/models/client/__init__.py
glean/models/client/entities.py
glean_helper-0.0.1.dist-info/METADATA
glean_helper-0.0.1.dist-info/WHEEL
glean_helper-0.0.1.dist-info/RECORD
